{
  "سينالكس" : {"id":"1","small_pic_url":"http://lorempixel.com/50/50/"},
  "بيساديل" : {"id":"2","small_pic_url":"http://lorempixel.com/50/50/"},
  "مينالكس" : {"id":"3","small_pic_url":"http://lorempixel.com/50/50/"},
  "امبورتال" : {"id":"4","small_pic_url":"http://lorempixel.com/50/50/"},
  "لكسولاك" : {"id":"5","small_pic_url":"http://lorempixel.com/50/50/"},
  "سيدالاك" : {"id":"6","small_pic_url":"http://lorempixel.com/50/50/"},
  "نورمالكس" : {"id":"7","small_pic_url":"http://lorempixel.com/50/50/"},
  "فوسفاتانيما" : {"id":"8","small_pic_url":"http://lorempixel.com/50/50/"},
  "لكسيبلنت" : {"id":"9","small_pic_url":"http://lorempixel.com/50/50/"},
  "جلسرين" : {"id":"10","small_pic_url":"http://lorempixel.com/50/50/"},
  "ابيكوافسلت" : {"id":"11","small_pic_url":"http://lorempixel.com/50/50/"},
  "بيداروز" : {"id":"12","small_pic_url":"http://lorempixel.com/50/50/"},
  "بورجيتون" : {"id":"13","small_pic_url":"http://lorempixel.com/50/50/"},
  "ابيلاكسين" : {"id":"14","small_pic_url":"http://lorempixel.com/50/50/"},
  "لاكسين" : {"id":"15","small_pic_url":"http://lorempixel.com/50/50/"},
  "دوفالاك" : {"id":"16","small_pic_url":"http://lorempixel.com/50/50/"},
  "لاكسولاك" : {"id":"17","small_pic_url":"http://lorempixel.com/50/50/"},
  "لاكتولااكس" : {"id":"18","small_pic_url":"http://lorempixel.com/50/50/"},
  "لاكسول باى" : {"id":"19","small_pic_url":"http://lorempixel.com/50/50/"},
  "انيماكس" : {"id":"20","small_pic_url":"http://lorempixel.com/50/50/"}
}
